callistoDownloader/__init__.py
callistoDownloader/callistoDownloader.py
callistoDownloader-0.4.4.4.dist-info/LICENSE
callistoDownloader-0.4.4.4.dist-info/METADATA
callistoDownloader-0.4.4.4.dist-info/WHEEL
callistoDownloader-0.4.4.4.dist-info/top_level.txt
callistoDownloader-0.4.4.4.dist-info/RECORD
