Metadata-Version: 2.1
Name: callistoDownloader
Version: 0.4.4.4
Summary: A python package to download e-Callisto spectrograms
Home-page: https://github.com/vvkrddy/callistoDownloader
Author: Vivek Reddy Pininti
Author-email: 
License: MIT
Keywords: Solar Physics Astronomy Spectrogram
Platform: UNKNOWN
Classifier: Development Status :: 3 - Alpha
Classifier: Intended Audience :: Science/Research
Classifier: Topic :: Scientific/Engineering :: Astronomy
Classifier: License :: OSI Approved :: MIT License
Classifier: Programming Language :: Python :: 3
License-File: LICENSE
Requires-Dist: requests
Requires-Dist: bs4
Requires-Dist: datetime
Requires-Dist: numpy
Requires-Dist: tqdm
